gmail_archiver/__init__.py
gmail_archiver/__main__.py
gmail_archiver/main.py
gmail_archiver/py.typed
gmail_archiver/typing.py
gmail_archiver/utils.py
gmail_archiver-0.0.5.dist-info/METADATA
gmail_archiver-0.0.5.dist-info/WHEEL
gmail_archiver-0.0.5.dist-info/entry_points.txt
gmail_archiver-0.0.5.dist-info/licenses/LICENSE.txt
gmail_archiver-0.0.5.dist-info/RECORD
